odoo/addons/sale_coupon_multi_gift/README.rst
odoo/addons/sale_coupon_multi_gift/__init__.py
odoo/addons/sale_coupon_multi_gift/__manifest__.py
odoo/addons/sale_coupon_multi_gift/i18n/sale_coupon_multi_gift.pot
odoo/addons/sale_coupon_multi_gift/migrations/13.0.2.0.0/post-migrate.py
odoo/addons/sale_coupon_multi_gift/migrations/13.0.2.0.0/pre-migrate.py
odoo/addons/sale_coupon_multi_gift/migrations/13.0.3.0.0/post-migrate.py
odoo/addons/sale_coupon_multi_gift/models/__init__.py
odoo/addons/sale_coupon_multi_gift/models/sale_coupon_program.py
odoo/addons/sale_coupon_multi_gift/models/sale_coupon_reward.py
odoo/addons/sale_coupon_multi_gift/models/sale_order.py
odoo/addons/sale_coupon_multi_gift/readme/CONFIGURE.rst
odoo/addons/sale_coupon_multi_gift/readme/CONTRIBUTORS.rst
odoo/addons/sale_coupon_multi_gift/readme/DESCRIPTION.rst
odoo/addons/sale_coupon_multi_gift/readme/ROADMAP.rst
odoo/addons/sale_coupon_multi_gift/readme/USAGE.rst
odoo/addons/sale_coupon_multi_gift/security/ir.model.access.csv
odoo/addons/sale_coupon_multi_gift/static/description/icon.png
odoo/addons/sale_coupon_multi_gift/static/description/index.html
odoo/addons/sale_coupon_multi_gift/tests/__init__.py
odoo/addons/sale_coupon_multi_gift/tests/test_sale_coupon_multi_gift.py
odoo/addons/sale_coupon_multi_gift/views/sale_coupon_program_views.xml
odoo13_addon_sale_coupon_multi_gift-13.0.3.0.1.dev2.dist-info/METADATA
odoo13_addon_sale_coupon_multi_gift-13.0.3.0.1.dev2.dist-info/WHEEL
odoo13_addon_sale_coupon_multi_gift-13.0.3.0.1.dev2.dist-info/top_level.txt
odoo13_addon_sale_coupon_multi_gift-13.0.3.0.1.dev2.dist-info/RECORD
